MANIFEST.in
README.rst
setup.py
idxtools.egg-info/PKG-INFO
idxtools.egg-info/SOURCES.txt
idxtools.egg-info/dependency_links.txt
idxtools.egg-info/entry_points.txt
idxtools.egg-info/requires.txt
idxtools.egg-info/top_level.txt
indexfile/__init__.py
indexfile/__main__.py
indexfile/dataset.py
indexfile/index.py
indexfile/utils.py
indexfile/cli/__init__.py
indexfile/cli/indexfile_main.py
indexfile/cli/indexfile_remove.py
indexfile/cli/indexfile_show.py
indexfile/cli/indexfile_update.py