Metadata-Version: 1.1
Name: idxtools
Version: 0.12.0
Summary: Indexfile API and tools
Home-page: https://github.com/emi80/idxtools
Author: Emilio Palumbo
Author-email: UNKNOWN
License: GNU General Public License (GPL)
Platform: lx64
Classifier: Development Status :: 4 - Beta
Classifier: Environment :: Console
Classifier: Intended Audience :: End Users/Desktop
Classifier: Intended Audience :: Developers
Classifier: License :: OSI Approved :: GNU General Public License (GPL)
Classifier: Operating System :: POSIX :: Linux
Classifier: Programming Language :: Python
Classifier: Topic :: Scientific/Engineering :: Bio-Informatics
